AUTHORS.txt
LICENSE.txt
MANIFEST.in
README.md
setup.cfg
setup.py
menpofit/__init__.py
menpofit/_static_version.py
menpofit/_version.py
menpofit/base.py
menpofit/builder.py
menpofit/checks.py
menpofit/differentiable.py
menpofit/fitter.py
menpofit/io.py
menpofit/modelinstance.py
menpofit/result.py
menpofit.egg-info/PKG-INFO
menpofit.egg-info/SOURCES.txt
menpofit.egg-info/dependency_links.txt
menpofit.egg-info/requires.txt
menpofit.egg-info/top_level.txt
menpofit/aam/__init__.py
menpofit/aam/base.py
menpofit/aam/fitter.py
menpofit/aam/pretrained.py
menpofit/aam/result.py
menpofit/aam/algorithm/__init__.py
menpofit/aam/algorithm/lk.py
menpofit/aam/algorithm/sd.py
menpofit/aps/__init__.py
menpofit/aps/base.py
menpofit/aps/fitter.py
menpofit/aps/result.py
menpofit/aps/algorithm/__init__.py
menpofit/aps/algorithm/gn.py
menpofit/atm/__init__.py
menpofit/atm/algorithm.py
menpofit/atm/base.py
menpofit/atm/fitter.py
menpofit/clm/__init__.py
menpofit/clm/base.py
menpofit/clm/fitter.py
menpofit/clm/algorithm/__init__.py
menpofit/clm/algorithm/gd.py
menpofit/clm/expert/__init__.py
menpofit/clm/expert/base.py
menpofit/clm/expert/ensemble.py
menpofit/dlib/__init__.py
menpofit/dlib/algorithm.py
menpofit/dlib/conversion.py
menpofit/dlib/fitter.py
menpofit/error/__init__.py
menpofit/error/base.py
menpofit/error/stats.py
menpofit/error/human/__init__.py
menpofit/error/human/face.py
menpofit/lk/__init__.py
menpofit/lk/algorithm.py
menpofit/lk/fitter.py
menpofit/lk/residual.py
menpofit/lk/result.py
menpofit/math/__init__.py
menpofit/math/correlationfilter.py
menpofit/math/fft_utils.py
menpofit/math/regression.py
menpofit/sdm/__init__.py
menpofit/sdm/fitter.py
menpofit/sdm/algorithm/__init__.py
menpofit/sdm/algorithm/base.py
menpofit/sdm/algorithm/fullyparametric.py
menpofit/sdm/algorithm/nonparametric.py
menpofit/sdm/algorithm/parametricappearance.py
menpofit/sdm/algorithm/parametricshape.py
menpofit/transform/__init__.py
menpofit/transform/homogeneous.py
menpofit/transform/modeldriven.py
menpofit/transform/piecewiseaffine.py
menpofit/transform/rbf.py
menpofit/transform/thinsplatesplines.py
menpofit/transform/test/__init__.py
