Metadata-Version: 1.0
Name: menpofit
Version: 0.7.0
Summary: Menpo's image feature point localisation (AAMs, SDMs, CLMs)
Home-page: UNKNOWN
Author: The Menpo Development Team
Author-email: james.booth08@imperial.ac.uk
License: UNKNOWN
Platform: UNKNOWN
